pytest_gherkin/__init__.py
pytest_gherkin/gherkin.py
pytest_gherkin/hooks.py
pytest_gherkin/legacy.py
pytest_gherkin/plugin.py
pytest_gherkin-0.1.7.dist-info/LICENSE
pytest_gherkin-0.1.7.dist-info/METADATA
pytest_gherkin-0.1.7.dist-info/WHEEL
pytest_gherkin-0.1.7.dist-info/entry_points.txt
pytest_gherkin-0.1.7.dist-info/top_level.txt
pytest_gherkin-0.1.7.dist-info/RECORD
