Metadata-Version: 2.1
Name: pytest-gherkin
Version: 0.1.7
Summary: A flexible framework for executing BDD gherkin tests
Home-page: https://github.com/nicois/pytest-gherkin
Author: Nick Farrell
Author-email: nicholas.farrell@gmail.com
Maintainer: Nick Farrell
Maintainer-email: nicholas.farrell@gmail.com
License: MIT
Platform: UNKNOWN
Classifier: Development Status :: 3 - Alpha
Classifier: Framework :: Pytest
Classifier: Intended Audience :: Developers
Classifier: Topic :: Software Development :: Testing :: BDD
Classifier: Topic :: Text Processing
Classifier: Programming Language :: Python :: 3
Classifier: License :: OSI Approved :: MIT License
Classifier: Operating System :: OS Independent
Classifier: Intended Audience :: Developers
Classifier: Programming Language :: Python
Classifier: Programming Language :: Python :: 3
Classifier: Programming Language :: Python :: 3.4
Classifier: Programming Language :: Python :: 3.5
Classifier: Programming Language :: Python :: 3.6
Classifier: Programming Language :: Python :: 3.7
Requires-Python: >=3.6
Requires-Dist: pytest (>=5.0.0)
Requires-Dist: gherkin-official (>=4.1.3)
